clamav_upload/__init__.py
clamav_upload/admin.py
clamav_upload/exceptions.py
clamav_upload/handlers.py
clamav_upload/models.py
django_clamav_upload-0.1.2.dist-info/DESCRIPTION.rst
django_clamav_upload-0.1.2.dist-info/METADATA
django_clamav_upload-0.1.2.dist-info/RECORD
django_clamav_upload-0.1.2.dist-info/WHEEL
django_clamav_upload-0.1.2.dist-info/metadata.json
django_clamav_upload-0.1.2.dist-info/top_level.txt
