Metadata-Version: 2.0
Name: django-clamav-upload
Version: 0.1.2
Summary: A simple upload handler for django that scans inbound streams for malicious content
Home-page: https://github.com/musashiXXX/django-clamav-upload
Author: Charles Hamilton
Author-email: musashi@nefaria.com
License: LICENSE.txt
Download-URL: https://github.com/musashiXXX/django-clamav-upload/tarball/0.1.2
Keywords: clamav django upload
Platform: UNKNOWN
Requires-Dist: Django (>=1.8.4)
Requires-Dist: pyClamd (==0.3.17)
